PyXtreme/__init__.py
PyXtreme-0.2.dist-info/LICENSE
PyXtreme-0.2.dist-info/METADATA
PyXtreme-0.2.dist-info/WHEEL
PyXtreme-0.2.dist-info/top_level.txt
PyXtreme-0.2.dist-info/RECORD
