Metadata-Version: 2.1
Name: PyXtreme
Version: 0.2
Summary: A simple to use package to get tons of results.
Home-page: UNKNOWN
Author: Rishikesh
Author-email: UNKNOWN
License: UNKNOWN
Platform: UNKNOWN
Requires-Dist: requests
